dbr/CommonServiceLocator.dll
dbr/ErrorHandler.dll
dbr/GalaSoft.MvvmLight.Extras.dll
dbr/GalaSoft.MvvmLight.dll
dbr/Hsc.dll
dbr/Newtonsoft.Json.dll
dbr/PresentationFramework.Aero2.dll
dbr/StationNetCore.dll
dbr/System.Windows.Interactivity.dll
dbr/WPFMessageBox.dll
dbr/Xceed.Wpf.DataGrid.dll
dbr/Xceed.Wpf.Toolkit.dll
dbr/__init__.py
dbr/imo.ico
dbr/log4net.dll
dbr/logo.png
dbr/version.txt
UI_dep_test1-0.0.1.dist-info/METADATA
UI_dep_test1-0.0.1.dist-info/WHEEL
UI_dep_test1-0.0.1.dist-info/top_level.txt
UI_dep_test1-0.0.1.dist-info/RECORD
