Metadata-Version: 2.1
Name: UI-dep-test1
Version: 0.0.1
Summary: UNKNOWN
Home-page: https://github.com/
Author: MYZY
Author-email: elton.tian@myzygroup.com
License: UNKNOWN
Platform: UNKNOWN
Classifier: Programming Language :: Python :: 3
Classifier: License :: OSI Approved :: MIT License
Classifier: Operating System :: OS Independent
Requires-Python: >=3
Requires-Dist: debug-world-swt (>=0.0.1)
